Metadata-Version: 1.0
Name: stat-utils
Version: 1.0
Summary: Utils for statistics
Home-page: https://github.com/KrozeRoll
Author: Alexander Osikov
Author-email: krozer95@gmail.com
License: BSD 2-clause
Platform: UNKNOWN
